{"nodes": [{"id": "f_kod_alphabots_rpa_mobile_de_scraper_src_scraper_vendor_scraper_py", "label": "vendor_scraper.py", "file_type": "code", "source_file": "F:\\kod\\alphabots_rpa\\mobile_de_scraper\\src\\scraper\\vendor_scraper.py", "source_location": "L1"}, {"id": "scraper_vendor_scraper_vendorscraper", "label": "VendorScraper", "file_type": "code", "source_file": "F:\\kod\\alphabots_rpa\\mobile_de_scraper\\src\\scraper\\vendor_scraper.py", "source_location": "L27"}, {"id": "scraper_vendor_scraper_vendorscraper_init", "label": ".__init__()", "file_type": "code", "source_file": "F:\\kod\\alphabots_rpa\\mobile_de_scraper\\src\\scraper\\vendor_scraper.py", "source_location": "L30"}, {"id": "scraper_vendor_scraper_vendorscraper_scrape_vendor", "label": ".scrape_vendor()", "file_type": "code", "source_file": "F:\\kod\\alphabots_rpa\\mobile_de_scraper\\src\\scraper\\vendor_scraper.py", "source_location": "L34"}, {"id": "scraper_vendor_scraper_vendorscraper_extract_ueber_uns", "label": "._extract_ueber_uns()", "file_type": "code", "source_file": "F:\\kod\\alphabots_rpa\\mobile_de_scraper\\src\\scraper\\vendor_scraper.py", "source_location": "L117"}, {"id": "scraper_vendor_scraper_vendorscraper_reveal_phone_numbers", "label": "._reveal_phone_numbers()", "file_type": "code", "source_file": "F:\\kod\\alphabots_rpa\\mobile_de_scraper\\src\\scraper\\vendor_scraper.py", "source_location": "L169"}, {"id": "scraper_vendor_scraper_vendorscraper_parse_modal_contacts", "label": "._parse_modal_contacts()", "file_type": "code", "source_file": "F:\\kod\\alphabots_rpa\\mobile_de_scraper\\src\\scraper\\vendor_scraper.py", "source_location": "L189"}, {"id": "scraper_vendor_scraper_vendorscraper_extract_impressum", "label": "._extract_impressum()", "file_type": "code", "source_file": "F:\\kod\\alphabots_rpa\\mobile_de_scraper\\src\\scraper\\vendor_scraper.py", "source_location": "L246"}, {"id": "scraper_vendor_scraper_format_phone", "label": "_format_phone()", "file_type": "code", "source_file": "F:\\kod\\alphabots_rpa\\mobile_de_scraper\\src\\scraper\\vendor_scraper.py", "source_location": "L283"}, {"id": "scraper_vendor_scraper_rationale_1", "label": "Vendor / dealer page scraper.  Extracts detailed vendor information from each de", "file_type": "rationale", "source_file": "F:\\kod\\alphabots_rpa\\mobile_de_scraper\\src\\scraper\\vendor_scraper.py", "source_location": "L1"}, {"id": "scraper_vendor_scraper_rationale_28", "label": "Extracts detailed information from a dealer's mobile.de page.", "file_type": "rationale", "source_file": "F:\\kod\\alphabots_rpa\\mobile_de_scraper\\src\\scraper\\vendor_scraper.py", "source_location": "L28"}, {"id": "scraper_vendor_scraper_rationale_36", "label": "Scrape a single vendor's detailed information.          Args:             dealer", "file_type": "rationale", "source_file": "F:\\kod\\alphabots_rpa\\mobile_de_scraper\\src\\scraper\\vendor_scraper.py", "source_location": "L36"}, {"id": "scraper_vendor_scraper_rationale_118", "label": "Click the '\u00dcber uns' button and extract contact info from the modal.          Th", "file_type": "rationale", "source_file": "F:\\kod\\alphabots_rpa\\mobile_de_scraper\\src\\scraper\\vendor_scraper.py", "source_location": "L118"}, {"id": "scraper_vendor_scraper_rationale_170", "label": "Click the eye icon to reveal full phone numbers.", "file_type": "rationale", "source_file": "F:\\kod\\alphabots_rpa\\mobile_de_scraper\\src\\scraper\\vendor_scraper.py", "source_location": "L170"}, {"id": "scraper_vendor_scraper_rationale_190", "label": "Parse contact information from the \u00dcber uns modal HTML.", "file_type": "rationale", "source_file": "F:\\kod\\alphabots_rpa\\mobile_de_scraper\\src\\scraper\\vendor_scraper.py", "source_location": "L190"}, {"id": "scraper_vendor_scraper_rationale_247", "label": "Expand Impressum & Rechtliches section for email.", "file_type": "rationale", "source_file": "F:\\kod\\alphabots_rpa\\mobile_de_scraper\\src\\scraper\\vendor_scraper.py", "source_location": "L247"}, {"id": "scraper_vendor_scraper_rationale_284", "label": "Format a phone number for readability.", "file_type": "rationale", "source_file": "F:\\kod\\alphabots_rpa\\mobile_de_scraper\\src\\scraper\\vendor_scraper.py", "source_location": "L284"}], "edges": [{"source": "f_kod_alphabots_rpa_mobile_de_scraper_src_scraper_vendor_scraper_py", "target": "asyncio", "relation": "imports", "context": "import", "confidence": "EXTRACTED", "source_file": "F:\\kod\\alphabots_rpa\\mobile_de_scraper\\src\\scraper\\vendor_scraper.py", "source_location": "L10", "weight": 1.0}, {"source": "f_kod_alphabots_rpa_mobile_de_scraper_src_scraper_vendor_scraper_py", "target": "logging", "relation": "imports", "context": "import", "confidence": "EXTRACTED", "source_file": "F:\\kod\\alphabots_rpa\\mobile_de_scraper\\src\\scraper\\vendor_scraper.py", "source_location": "L11", "weight": 1.0}, {"source": "f_kod_alphabots_rpa_mobile_de_scraper_src_scraper_vendor_scraper_py", "target": "re", "relation": "imports", "context": "import", "confidence": "EXTRACTED", "source_file": "F:\\kod\\alphabots_rpa\\mobile_de_scraper\\src\\scraper\\vendor_scraper.py", "source_location": "L12", "weight": 1.0}, {"source": "f_kod_alphabots_rpa_mobile_de_scraper_src_scraper_vendor_scraper_py", "target": "typing", "relation": "imports_from", "context": "import", "confidence": "EXTRACTED", "source_file": "F:\\kod\\alphabots_rpa\\mobile_de_scraper\\src\\scraper\\vendor_scraper.py", "source_location": "L13", "weight": 1.0}, {"source": "f_kod_alphabots_rpa_mobile_de_scraper_src_scraper_vendor_scraper_py", "target": "src_config", "relation": "imports_from", "context": "import", "confidence": "EXTRACTED", "source_file": "F:\\kod\\alphabots_rpa\\mobile_de_scraper\\src\\scraper\\vendor_scraper.py", "source_location": "L15", "weight": 1.0}, {"source": "f_kod_alphabots_rpa_mobile_de_scraper_src_scraper_vendor_scraper_py", "target": "src_scraper_browser", "relation": "imports_from", "context": "import", "confidence": "EXTRACTED", "source_file": "F:\\kod\\alphabots_rpa\\mobile_de_scraper\\src\\scraper\\vendor_scraper.py", "source_location": "L16", "weight": 1.0}, {"source": "f_kod_alphabots_rpa_mobile_de_scraper_src_scraper_vendor_scraper_py", "target": "src_scraper_parsers", "relation": "imports_from", "context": "import", "confidence": "EXTRACTED", "source_file": "F:\\kod\\alphabots_rpa\\mobile_de_scraper\\src\\scraper\\vendor_scraper.py", "source_location": "L17", "weight": 1.0}, {"source": "f_kod_alphabots_rpa_mobile_de_scraper_src_scraper_vendor_scraper_py", "target": "scraper_vendor_scraper_vendorscraper", "relation": "contains", "confidence": "EXTRACTED", "source_file": "F:\\kod\\alphabots_rpa\\mobile_de_scraper\\src\\scraper\\vendor_scraper.py", "source_location": "L27", "weight": 1.0}, {"source": "scraper_vendor_scraper_vendorscraper", "target": "scraper_vendor_scraper_vendorscraper_init", "relation": "method", "confidence": "EXTRACTED", "source_file": "F:\\kod\\alphabots_rpa\\mobile_de_scraper\\src\\scraper\\vendor_scraper.py", "source_location": "L30", "weight": 1.0}, {"source": "scraper_vendor_scraper_vendorscraper", "target": "scraper_vendor_scraper_vendorscraper_scrape_vendor", "relation": "method", "confidence": "EXTRACTED", "source_file": "F:\\kod\\alphabots_rpa\\mobile_de_scraper\\src\\scraper\\vendor_scraper.py", "source_location": "L34", "weight": 1.0}, {"source": "scraper_vendor_scraper_vendorscraper", "target": "scraper_vendor_scraper_vendorscraper_extract_ueber_uns", "relation": "method", "confidence": "EXTRACTED", "source_file": "F:\\kod\\alphabots_rpa\\mobile_de_scraper\\src\\scraper\\vendor_scraper.py", "source_location": "L117", "weight": 1.0}, {"source": "scraper_vendor_scraper_vendorscraper", "target": "scraper_vendor_scraper_vendorscraper_reveal_phone_numbers", "relation": "method", "confidence": "EXTRACTED", "source_file": "F:\\kod\\alphabots_rpa\\mobile_de_scraper\\src\\scraper\\vendor_scraper.py", "source_location": "L169", "weight": 1.0}, {"source": "scraper_vendor_scraper_vendorscraper", "target": "scraper_vendor_scraper_vendorscraper_parse_modal_contacts", "relation": "method", "confidence": "EXTRACTED", "source_file": "F:\\kod\\alphabots_rpa\\mobile_de_scraper\\src\\scraper\\vendor_scraper.py", "source_location": "L189", "weight": 1.0}, {"source": "scraper_vendor_scraper_vendorscraper", "target": "scraper_vendor_scraper_vendorscraper_extract_impressum", "relation": "method", "confidence": "EXTRACTED", "source_file": "F:\\kod\\alphabots_rpa\\mobile_de_scraper\\src\\scraper\\vendor_scraper.py", "source_location": "L246", "weight": 1.0}, {"source": "f_kod_alphabots_rpa_mobile_de_scraper_src_scraper_vendor_scraper_py", "target": "scraper_vendor_scraper_format_phone", "relation": "contains", "confidence": "EXTRACTED", "source_file": "F:\\kod\\alphabots_rpa\\mobile_de_scraper\\src\\scraper\\vendor_scraper.py", "source_location": "L283", "weight": 1.0}, {"source": "scraper_vendor_scraper_vendorscraper_scrape_vendor", "target": "scraper_vendor_scraper_format_phone", "relation": "calls", "context": "call", "confidence": "EXTRACTED", "source_file": "F:\\kod\\alphabots_rpa\\mobile_de_scraper\\src\\scraper\\vendor_scraper.py", "source_location": "L103", "weight": 1.0}, {"source": "scraper_vendor_scraper_vendorscraper_scrape_vendor", "target": "scraper_vendor_scraper_vendorscraper_extract_ueber_uns", "relation": "calls", "context": "call", "confidence": "EXTRACTED", "source_file": "F:\\kod\\alphabots_rpa\\mobile_de_scraper\\src\\scraper\\vendor_scraper.py", "source_location": "L113", "weight": 1.0}, {"source": "scraper_vendor_scraper_vendorscraper_extract_ueber_uns", "target": "scraper_vendor_scraper_vendorscraper_reveal_phone_numbers", "relation": "calls", "context": "call", "confidence": "EXTRACTED", "source_file": "F:\\kod\\alphabots_rpa\\mobile_de_scraper\\src\\scraper\\vendor_scraper.py", "source_location": "L145", "weight": 1.0}, {"source": "scraper_vendor_scraper_vendorscraper_extract_ueber_uns", "target": "scraper_vendor_scraper_vendorscraper_parse_modal_contacts", "relation": "calls", "context": "call", "confidence": "EXTRACTED", "source_file": "F:\\kod\\alphabots_rpa\\mobile_de_scraper\\src\\scraper\\vendor_scraper.py", "source_location": "L149", "weight": 1.0}, {"source": "scraper_vendor_scraper_vendorscraper_extract_ueber_uns", "target": "scraper_vendor_scraper_vendorscraper_extract_impressum", "relation": "calls", "context": "call", "confidence": "EXTRACTED", "source_file": "F:\\kod\\alphabots_rpa\\mobile_de_scraper\\src\\scraper\\vendor_scraper.py", "source_location": "L152", "weight": 1.0}, {"source": "scraper_vendor_scraper_rationale_1", "target": "f_kod_alphabots_rpa_mobile_de_scraper_src_scraper_vendor_scraper_py", "relation": "rationale_for", "confidence": "EXTRACTED", "source_file": "F:\\kod\\alphabots_rpa\\mobile_de_scraper\\src\\scraper\\vendor_scraper.py", "source_location": "L1", "weight": 1.0}, {"source": "scraper_vendor_scraper_rationale_28", "target": "scraper_vendor_scraper_vendorscraper", "relation": "rationale_for", "confidence": "EXTRACTED", "source_file": "F:\\kod\\alphabots_rpa\\mobile_de_scraper\\src\\scraper\\vendor_scraper.py", "source_location": "L28", "weight": 1.0}, {"source": "scraper_vendor_scraper_rationale_36", "target": "scraper_vendor_scraper_vendorscraper_scrape_vendor", "relation": "rationale_for", "confidence": "EXTRACTED", "source_file": "F:\\kod\\alphabots_rpa\\mobile_de_scraper\\src\\scraper\\vendor_scraper.py", "source_location": "L36", "weight": 1.0}, {"source": "scraper_vendor_scraper_rationale_118", "target": "scraper_vendor_scraper_vendorscraper_extract_ueber_uns", "relation": "rationale_for", "confidence": "EXTRACTED", "source_file": "F:\\kod\\alphabots_rpa\\mobile_de_scraper\\src\\scraper\\vendor_scraper.py", "source_location": "L118", "weight": 1.0}, {"source": "scraper_vendor_scraper_rationale_170", "target": "scraper_vendor_scraper_vendorscraper_reveal_phone_numbers", "relation": "rationale_for", "confidence": "EXTRACTED", "source_file": "F:\\kod\\alphabots_rpa\\mobile_de_scraper\\src\\scraper\\vendor_scraper.py", "source_location": "L170", "weight": 1.0}, {"source": "scraper_vendor_scraper_rationale_190", "target": "scraper_vendor_scraper_vendorscraper_parse_modal_contacts", "relation": "rationale_for", "confidence": "EXTRACTED", "source_file": "F:\\kod\\alphabots_rpa\\mobile_de_scraper\\src\\scraper\\vendor_scraper.py", "source_location": "L190", "weight": 1.0}, {"source": "scraper_vendor_scraper_rationale_247", "target": "scraper_vendor_scraper_vendorscraper_extract_impressum", "relation": "rationale_for", "confidence": "EXTRACTED", "source_file": "F:\\kod\\alphabots_rpa\\mobile_de_scraper\\src\\scraper\\vendor_scraper.py", "source_location": "L247", "weight": 1.0}, {"source": "scraper_vendor_scraper_rationale_284", "target": "scraper_vendor_scraper_format_phone", "relation": "rationale_for", "confidence": "EXTRACTED", "source_file": "F:\\kod\\alphabots_rpa\\mobile_de_scraper\\src\\scraper\\vendor_scraper.py", "source_location": "L284", "weight": 1.0}], "raw_calls": [{"caller_nid": "scraper_vendor_scraper_vendorscraper_scrape_vendor", "callee": "info", "is_member_call": true, "source_file": "F:\\kod\\alphabots_rpa\\mobile_de_scraper\\src\\scraper\\vendor_scraper.py", "source_location": "L47"}, {"caller_nid": "scraper_vendor_scraper_vendorscraper_scrape_vendor", "callee": "get", "is_member_call": true, "source_file": "F:\\kod\\alphabots_rpa\\mobile_de_scraper\\src\\scraper\\vendor_scraper.py", "source_location": "L50"}, {"caller_nid": "scraper_vendor_scraper_vendorscraper_scrape_vendor", "callee": "get", "is_member_call": true, "source_file": "F:\\kod\\alphabots_rpa\\mobile_de_scraper\\src\\scraper\\vendor_scraper.py", "source_location": "L51"}, {"caller_nid": "scraper_vendor_scraper_vendorscraper_scrape_vendor", "callee": "get", "is_member_call": true, "source_file": "F:\\kod\\alphabots_rpa\\mobile_de_scraper\\src\\scraper\\vendor_scraper.py", "source_location": "L52"}, {"caller_nid": "scraper_vendor_scraper_vendorscraper_scrape_vendor", "callee": "get", "is_member_call": true, "source_file": "F:\\kod\\alphabots_rpa\\mobile_de_scraper\\src\\scraper\\vendor_scraper.py", "source_location": "L53"}, {"caller_nid": "scraper_vendor_scraper_vendorscraper_scrape_vendor", "callee": "safe_goto", "is_member_call": true, "source_file": "F:\\kod\\alphabots_rpa\\mobile_de_scraper\\src\\scraper\\vendor_scraper.py", "source_location": "L67"}, {"caller_nid": "scraper_vendor_scraper_vendorscraper_scrape_vendor", "callee": "warning", "is_member_call": true, "source_file": "F:\\kod\\alphabots_rpa\\mobile_de_scraper\\src\\scraper\\vendor_scraper.py", "source_location": "L69"}, {"caller_nid": "scraper_vendor_scraper_vendorscraper_scrape_vendor", "callee": "sleep", "is_member_call": true, "source_file": "F:\\kod\\alphabots_rpa\\mobile_de_scraper\\src\\scraper\\vendor_scraper.py", "source_location": "L72"}, {"caller_nid": "scraper_vendor_scraper_vendorscraper_scrape_vendor", "callee": "get_page_html", "is_member_call": true, "source_file": "F:\\kod\\alphabots_rpa\\mobile_de_scraper\\src\\scraper\\vendor_scraper.py", "source_location": "L75"}, {"caller_nid": "scraper_vendor_scraper_vendorscraper_scrape_vendor", "callee": "parse_vendor_next_data", "is_member_call": false, "source_file": "F:\\kod\\alphabots_rpa\\mobile_de_scraper\\src\\scraper\\vendor_scraper.py", "source_location": "L80"}, {"caller_nid": "scraper_vendor_scraper_vendorscraper_scrape_vendor", "callee": "get", "is_member_call": true, "source_file": "F:\\kod\\alphabots_rpa\\mobile_de_scraper\\src\\scraper\\vendor_scraper.py", "source_location": "L82"}, {"caller_nid": "scraper_vendor_scraper_vendorscraper_scrape_vendor", "callee": "get", "is_member_call": true, "source_file": "F:\\kod\\alphabots_rpa\\mobile_de_scraper\\src\\scraper\\vendor_scraper.py", "source_location": "L83"}, {"caller_nid": "scraper_vendor_scraper_vendorscraper_scrape_vendor", "callee": "get", "is_member_call": true, "source_file": "F:\\kod\\alphabots_rpa\\mobile_de_scraper\\src\\scraper\\vendor_scraper.py", "source_location": "L84"}, {"caller_nid": "scraper_vendor_scraper_vendorscraper_scrape_vendor", "callee": "get", "is_member_call": true, "source_file": "F:\\kod\\alphabots_rpa\\mobile_de_scraper\\src\\scraper\\vendor_scraper.py", "source_location": "L85"}, {"caller_nid": "scraper_vendor_scraper_vendorscraper_scrape_vendor", "callee": "get", "is_member_call": true, "source_file": "F:\\kod\\alphabots_rpa\\mobile_de_scraper\\src\\scraper\\vendor_scraper.py", "source_location": "L86"}, {"caller_nid": "scraper_vendor_scraper_vendorscraper_scrape_vendor", "callee": "get", "is_member_call": true, "source_file": "F:\\kod\\alphabots_rpa\\mobile_de_scraper\\src\\scraper\\vendor_scraper.py", "source_location": "L87"}, {"caller_nid": "scraper_vendor_scraper_vendorscraper_scrape_vendor", "callee": "get", "is_member_call": true, "source_file": "F:\\kod\\alphabots_rpa\\mobile_de_scraper\\src\\scraper\\vendor_scraper.py", "source_location": "L88"}, {"caller_nid": "scraper_vendor_scraper_vendorscraper_scrape_vendor", "callee": "get", "is_member_call": true, "source_file": "F:\\kod\\alphabots_rpa\\mobile_de_scraper\\src\\scraper\\vendor_scraper.py", "source_location": "L89"}, {"caller_nid": "scraper_vendor_scraper_vendorscraper_scrape_vendor", "callee": "get", "is_member_call": true, "source_file": "F:\\kod\\alphabots_rpa\\mobile_de_scraper\\src\\scraper\\vendor_scraper.py", "source_location": "L90"}, {"caller_nid": "scraper_vendor_scraper_vendorscraper_scrape_vendor", "callee": "get", "is_member_call": true, "source_file": "F:\\kod\\alphabots_rpa\\mobile_de_scraper\\src\\scraper\\vendor_scraper.py", "source_location": "L91"}, {"caller_nid": "scraper_vendor_scraper_vendorscraper_scrape_vendor", "callee": "get", "is_member_call": true, "source_file": "F:\\kod\\alphabots_rpa\\mobile_de_scraper\\src\\scraper\\vendor_scraper.py", "source_location": "L92"}, {"caller_nid": "scraper_vendor_scraper_vendorscraper_scrape_vendor", "callee": "get", "is_member_call": true, "source_file": "F:\\kod\\alphabots_rpa\\mobile_de_scraper\\src\\scraper\\vendor_scraper.py", "source_location": "L93"}, {"caller_nid": "scraper_vendor_scraper_vendorscraper_scrape_vendor", "callee": "parse_vendor_json_ld", "is_member_call": false, "source_file": "F:\\kod\\alphabots_rpa\\mobile_de_scraper\\src\\scraper\\vendor_scraper.py", "source_location": "L96"}, {"caller_nid": "scraper_vendor_scraper_vendorscraper_scrape_vendor", "callee": "get", "is_member_call": true, "source_file": "F:\\kod\\alphabots_rpa\\mobile_de_scraper\\src\\scraper\\vendor_scraper.py", "source_location": "L98"}, {"caller_nid": "scraper_vendor_scraper_vendorscraper_scrape_vendor", "callee": "get", "is_member_call": true, "source_file": "F:\\kod\\alphabots_rpa\\mobile_de_scraper\\src\\scraper\\vendor_scraper.py", "source_location": "L99"}, {"caller_nid": "scraper_vendor_scraper_vendorscraper_scrape_vendor", "callee": "get", "is_member_call": true, "source_file": "F:\\kod\\alphabots_rpa\\mobile_de_scraper\\src\\scraper\\vendor_scraper.py", "source_location": "L100"}, {"caller_nid": "scraper_vendor_scraper_vendorscraper_scrape_vendor", "callee": "get", "is_member_call": true, "source_file": "F:\\kod\\alphabots_rpa\\mobile_de_scraper\\src\\scraper\\vendor_scraper.py", "source_location": "L101"}, {"caller_nid": "scraper_vendor_scraper_vendorscraper_scrape_vendor", "callee": "get", "is_member_call": true, "source_file": "F:\\kod\\alphabots_rpa\\mobile_de_scraper\\src\\scraper\\vendor_scraper.py", "source_location": "L102"}, {"caller_nid": "scraper_vendor_scraper_vendorscraper_scrape_vendor", "callee": "get", "is_member_call": true, "source_file": "F:\\kod\\alphabots_rpa\\mobile_de_scraper\\src\\scraper\\vendor_scraper.py", "source_location": "L104"}, {"caller_nid": "scraper_vendor_scraper_vendorscraper_scrape_vendor", "callee": "parse_vendor_vehicle_count", "is_member_call": false, "source_file": "F:\\kod\\alphabots_rpa\\mobile_de_scraper\\src\\scraper\\vendor_scraper.py", "source_location": "L108"}, {"caller_nid": "scraper_vendor_scraper_vendorscraper_extract_ueber_uns", "callee": "locator", "is_member_call": true, "source_file": "F:\\kod\\alphabots_rpa\\mobile_de_scraper\\src\\scraper\\vendor_scraper.py", "source_location": "L132"}, {"caller_nid": "scraper_vendor_scraper_vendorscraper_extract_ueber_uns", "callee": "count", "is_member_call": true, "source_file": "F:\\kod\\alphabots_rpa\\mobile_de_scraper\\src\\scraper\\vendor_scraper.py", "source_location": "L137"}, {"caller_nid": "scraper_vendor_scraper_vendorscraper_extract_ueber_uns", "callee": "debug", "is_member_call": true, "source_file": "F:\\kod\\alphabots_rpa\\mobile_de_scraper\\src\\scraper\\vendor_scraper.py", "source_location": "L138"}, {"caller_nid": "scraper_vendor_scraper_vendorscraper_extract_ueber_uns", "callee": "click", "is_member_call": true, "source_file": "F:\\kod\\alphabots_rpa\\mobile_de_scraper\\src\\scraper\\vendor_scraper.py", "source_location": "L141"}, {"caller_nid": "scraper_vendor_scraper_vendorscraper_extract_ueber_uns", "callee": "sleep", "is_member_call": true, "source_file": "F:\\kod\\alphabots_rpa\\mobile_de_scraper\\src\\scraper\\vendor_scraper.py", "source_location": "L142"}, {"caller_nid": "scraper_vendor_scraper_vendorscraper_extract_ueber_uns", "callee": "content", "is_member_call": true, "source_file": "F:\\kod\\alphabots_rpa\\mobile_de_scraper\\src\\scraper\\vendor_scraper.py", "source_location": "L148"}, {"caller_nid": "scraper_vendor_scraper_vendorscraper_extract_ueber_uns", "callee": "locator", "is_member_call": true, "source_file": "F:\\kod\\alphabots_rpa\\mobile_de_scraper\\src\\scraper\\vendor_scraper.py", "source_location": "L156"}, {"caller_nid": "scraper_vendor_scraper_vendorscraper_extract_ueber_uns", "callee": "count", "is_member_call": true, "source_file": "F:\\kod\\alphabots_rpa\\mobile_de_scraper\\src\\scraper\\vendor_scraper.py", "source_location": "L160"}, {"caller_nid": "scraper_vendor_scraper_vendorscraper_extract_ueber_uns", "callee": "click", "is_member_call": true, "source_file": "F:\\kod\\alphabots_rpa\\mobile_de_scraper\\src\\scraper\\vendor_scraper.py", "source_location": "L161"}, {"caller_nid": "scraper_vendor_scraper_vendorscraper_extract_ueber_uns", "callee": "sleep", "is_member_call": true, "source_file": "F:\\kod\\alphabots_rpa\\mobile_de_scraper\\src\\scraper\\vendor_scraper.py", "source_location": "L162"}, {"caller_nid": "scraper_vendor_scraper_vendorscraper_extract_ueber_uns", "callee": "debug", "is_member_call": true, "source_file": "F:\\kod\\alphabots_rpa\\mobile_de_scraper\\src\\scraper\\vendor_scraper.py", "source_location": "L167"}, {"caller_nid": "scraper_vendor_scraper_vendorscraper_reveal_phone_numbers", "callee": "locator", "is_member_call": true, "source_file": "F:\\kod\\alphabots_rpa\\mobile_de_scraper\\src\\scraper\\vendor_scraper.py", "source_location": "L173"}, {"caller_nid": "scraper_vendor_scraper_vendorscraper_reveal_phone_numbers", "callee": "range", "is_member_call": false, "source_file": "F:\\kod\\alphabots_rpa\\mobile_de_scraper\\src\\scraper\\vendor_scraper.py", "source_location": "L179"}, {"caller_nid": "scraper_vendor_scraper_vendorscraper_reveal_phone_numbers", "callee": "min", "is_member_call": false, "source_file": "F:\\kod\\alphabots_rpa\\mobile_de_scraper\\src\\scraper\\vendor_scraper.py", "source_location": "L179"}, {"caller_nid": "scraper_vendor_scraper_vendorscraper_reveal_phone_numbers", "callee": "count", "is_member_call": true, "source_file": "F:\\kod\\alphabots_rpa\\mobile_de_scraper\\src\\scraper\\vendor_scraper.py", "source_location": "L179"}, {"caller_nid": "scraper_vendor_scraper_vendorscraper_reveal_phone_numbers", "callee": "click", "is_member_call": true, "source_file": "F:\\kod\\alphabots_rpa\\mobile_de_scraper\\src\\scraper\\vendor_scraper.py", "source_location": "L181"}, {"caller_nid": "scraper_vendor_scraper_vendorscraper_reveal_phone_numbers", "callee": "nth", "is_member_call": true, "source_file": "F:\\kod\\alphabots_rpa\\mobile_de_scraper\\src\\scraper\\vendor_scraper.py", "source_location": "L181"}, {"caller_nid": "scraper_vendor_scraper_vendorscraper_reveal_phone_numbers", "callee": "sleep", "is_member_call": true, "source_file": "F:\\kod\\alphabots_rpa\\mobile_de_scraper\\src\\scraper\\vendor_scraper.py", "source_location": "L182"}, {"caller_nid": "scraper_vendor_scraper_vendorscraper_reveal_phone_numbers", "callee": "debug", "is_member_call": true, "source_file": "F:\\kod\\alphabots_rpa\\mobile_de_scraper\\src\\scraper\\vendor_scraper.py", "source_location": "L183"}, {"caller_nid": "scraper_vendor_scraper_vendorscraper_reveal_phone_numbers", "callee": "debug", "is_member_call": true, "source_file": "F:\\kod\\alphabots_rpa\\mobile_de_scraper\\src\\scraper\\vendor_scraper.py", "source_location": "L187"}, {"caller_nid": "scraper_vendor_scraper_vendorscraper_parse_modal_contacts", "callee": "BeautifulSoup", "is_member_call": false, "source_file": "F:\\kod\\alphabots_rpa\\mobile_de_scraper\\src\\scraper\\vendor_scraper.py", "source_location": "L193"}, {"caller_nid": "scraper_vendor_scraper_vendorscraper_parse_modal_contacts", "callee": "clean_text", "is_member_call": false, "source_file": "F:\\kod\\alphabots_rpa\\mobile_de_scraper\\src\\scraper\\vendor_scraper.py", "source_location": "L194"}, {"caller_nid": "scraper_vendor_scraper_vendorscraper_parse_modal_contacts", "callee": "get_text", "is_member_call": true, "source_file": "F:\\kod\\alphabots_rpa\\mobile_de_scraper\\src\\scraper\\vendor_scraper.py", "source_location": "L194"}, {"caller_nid": "scraper_vendor_scraper_vendorscraper_parse_modal_contacts", "callee": "search", "is_member_call": true, "source_file": "F:\\kod\\alphabots_rpa\\mobile_de_scraper\\src\\scraper\\vendor_scraper.py", "source_location": "L210"}, {"caller_nid": "scraper_vendor_scraper_vendorscraper_parse_modal_contacts", "callee": "strip", "is_member_call": true, "source_file": "F:\\kod\\alphabots_rpa\\mobile_de_scraper\\src\\scraper\\vendor_scraper.py", "source_location": "L212"}, {"caller_nid": "scraper_vendor_scraper_vendorscraper_parse_modal_contacts", "callee": "group", "is_member_call": true, "source_file": "F:\\kod\\alphabots_rpa\\mobile_de_scraper\\src\\scraper\\vendor_scraper.py", "source_location": "L212"}, {"caller_nid": "scraper_vendor_scraper_vendorscraper_parse_modal_contacts", "callee": "sub", "is_member_call": true, "source_file": "F:\\kod\\alphabots_rpa\\mobile_de_scraper\\src\\scraper\\vendor_scraper.py", "source_location": "L213"}, {"caller_nid": "scraper_vendor_scraper_vendorscraper_parse_modal_contacts", "callee": "len", "is_member_call": false, "source_file": "F:\\kod\\alphabots_rpa\\mobile_de_scraper\\src\\scraper\\vendor_scraper.py", "source_location": "L214"}, {"caller_nid": "scraper_vendor_scraper_vendorscraper_parse_modal_contacts", "callee": "get", "is_member_call": true, "source_file": "F:\\kod\\alphabots_rpa\\mobile_de_scraper\\src\\scraper\\vendor_scraper.py", "source_location": "L215"}, {"caller_nid": "scraper_vendor_scraper_vendorscraper_parse_modal_contacts", "callee": "find_all", "is_member_call": true, "source_file": "F:\\kod\\alphabots_rpa\\mobile_de_scraper\\src\\scraper\\vendor_scraper.py", "source_location": "L218"}, {"caller_nid": "scraper_vendor_scraper_vendorscraper_parse_modal_contacts", "callee": "get_text", "is_member_call": true, "source_file": "F:\\kod\\alphabots_rpa\\mobile_de_scraper\\src\\scraper\\vendor_scraper.py", "source_location": "L220"}, {"caller_nid": "scraper_vendor_scraper_vendorscraper_parse_modal_contacts", "callee": "startswith", "is_member_call": true, "source_file": "F:\\kod\\alphabots_rpa\\mobile_de_scraper\\src\\scraper\\vendor_scraper.py", "source_location": "L221"}, {"caller_nid": "scraper_vendor_scraper_vendorscraper_parse_modal_contacts", "callee": "len", "is_member_call": false, "source_file": "F:\\kod\\alphabots_rpa\\mobile_de_scraper\\src\\scraper\\vendor_scraper.py", "source_location": "L221"}, {"caller_nid": "scraper_vendor_scraper_vendorscraper_parse_modal_contacts", "callee": "get", "is_member_call": true, "source_file": "F:\\kod\\alphabots_rpa\\mobile_de_scraper\\src\\scraper\\vendor_scraper.py", "source_location": "L222"}, {"caller_nid": "scraper_vendor_scraper_vendorscraper_parse_modal_contacts", "callee": "get", "is_member_call": true, "source_file": "F:\\kod\\alphabots_rpa\\mobile_de_scraper\\src\\scraper\\vendor_scraper.py", "source_location": "L226"}, {"caller_nid": "scraper_vendor_scraper_vendorscraper_parse_modal_contacts", "callee": "startswith", "is_member_call": true, "source_file": "F:\\kod\\alphabots_rpa\\mobile_de_scraper\\src\\scraper\\vendor_scraper.py", "source_location": "L227"}, {"caller_nid": "scraper_vendor_scraper_vendorscraper_parse_modal_contacts", "callee": "search", "is_member_call": true, "source_file": "F:\\kod\\alphabots_rpa\\mobile_de_scraper\\src\\scraper\\vendor_scraper.py", "source_location": "L233"}, {"caller_nid": "scraper_vendor_scraper_vendorscraper_parse_modal_contacts", "callee": "strip", "is_member_call": true, "source_file": "F:\\kod\\alphabots_rpa\\mobile_de_scraper\\src\\scraper\\vendor_scraper.py", "source_location": "L235"}, {"caller_nid": "scraper_vendor_scraper_vendorscraper_parse_modal_contacts", "callee": "group", "is_member_call": true, "source_file": "F:\\kod\\alphabots_rpa\\mobile_de_scraper\\src\\scraper\\vendor_scraper.py", "source_location": "L235"}, {"caller_nid": "scraper_vendor_scraper_vendorscraper_parse_modal_contacts", "callee": "clean_text", "is_member_call": false, "source_file": "F:\\kod\\alphabots_rpa\\mobile_de_scraper\\src\\scraper\\vendor_scraper.py", "source_location": "L236"}, {"caller_nid": "scraper_vendor_scraper_vendorscraper_parse_modal_contacts", "callee": "search", "is_member_call": true, "source_file": "F:\\kod\\alphabots_rpa\\mobile_de_scraper\\src\\scraper\\vendor_scraper.py", "source_location": "L239"}, {"caller_nid": "scraper_vendor_scraper_vendorscraper_parse_modal_contacts", "callee": "group", "is_member_call": true, "source_file": "F:\\kod\\alphabots_rpa\\mobile_de_scraper\\src\\scraper\\vendor_scraper.py", "source_location": "L242"}, {"caller_nid": "scraper_vendor_scraper_vendorscraper_parse_modal_contacts", "callee": "clean_text", "is_member_call": false, "source_file": "F:\\kod\\alphabots_rpa\\mobile_de_scraper\\src\\scraper\\vendor_scraper.py", "source_location": "L244"}, {"caller_nid": "scraper_vendor_scraper_vendorscraper_parse_modal_contacts", "callee": "group", "is_member_call": true, "source_file": "F:\\kod\\alphabots_rpa\\mobile_de_scraper\\src\\scraper\\vendor_scraper.py", "source_location": "L244"}, {"caller_nid": "scraper_vendor_scraper_vendorscraper_extract_impressum", "callee": "locator", "is_member_call": true, "source_file": "F:\\kod\\alphabots_rpa\\mobile_de_scraper\\src\\scraper\\vendor_scraper.py", "source_location": "L250"}, {"caller_nid": "scraper_vendor_scraper_vendorscraper_extract_impressum", "callee": "count", "is_member_call": true, "source_file": "F:\\kod\\alphabots_rpa\\mobile_de_scraper\\src\\scraper\\vendor_scraper.py", "source_location": "L253"}, {"caller_nid": "scraper_vendor_scraper_vendorscraper_extract_impressum", "callee": "click", "is_member_call": true, "source_file": "F:\\kod\\alphabots_rpa\\mobile_de_scraper\\src\\scraper\\vendor_scraper.py", "source_location": "L254"}, {"caller_nid": "scraper_vendor_scraper_vendorscraper_extract_impressum", "callee": "sleep", "is_member_call": true, "source_file": "F:\\kod\\alphabots_rpa\\mobile_de_scraper\\src\\scraper\\vendor_scraper.py", "source_location": "L255"}, {"caller_nid": "scraper_vendor_scraper_vendorscraper_extract_impressum", "callee": "content", "is_member_call": true, "source_file": "F:\\kod\\alphabots_rpa\\mobile_de_scraper\\src\\scraper\\vendor_scraper.py", "source_location": "L258"}, {"caller_nid": "scraper_vendor_scraper_vendorscraper_extract_impressum", "callee": "BeautifulSoup", "is_member_call": false, "source_file": "F:\\kod\\alphabots_rpa\\mobile_de_scraper\\src\\scraper\\vendor_scraper.py", "source_location": "L260"}, {"caller_nid": "scraper_vendor_scraper_vendorscraper_extract_impressum", "callee": "find_all", "is_member_call": true, "source_file": "F:\\kod\\alphabots_rpa\\mobile_de_scraper\\src\\scraper\\vendor_scraper.py", "source_location": "L263"}, {"caller_nid": "scraper_vendor_scraper_vendorscraper_extract_impressum", "callee": "startswith", "is_member_call": true, "source_file": "F:\\kod\\alphabots_rpa\\mobile_de_scraper\\src\\scraper\\vendor_scraper.py", "source_location": "L265"}, {"caller_nid": "scraper_vendor_scraper_vendorscraper_extract_impressum", "callee": "strip", "is_member_call": true, "source_file": "F:\\kod\\alphabots_rpa\\mobile_de_scraper\\src\\scraper\\vendor_scraper.py", "source_location": "L266"}, {"caller_nid": "scraper_vendor_scraper_vendorscraper_extract_impressum", "callee": "replace", "is_member_call": true, "source_file": "F:\\kod\\alphabots_rpa\\mobile_de_scraper\\src\\scraper\\vendor_scraper.py", "source_location": "L266"}, {"caller_nid": "scraper_vendor_scraper_vendorscraper_extract_impressum", "callee": "compile", "is_member_call": true, "source_file": "F:\\kod\\alphabots_rpa\\mobile_de_scraper\\src\\scraper\\vendor_scraper.py", "source_location": "L273"}, {"caller_nid": "scraper_vendor_scraper_vendorscraper_extract_impressum", "callee": "get_text", "is_member_call": true, "source_file": "F:\\kod\\alphabots_rpa\\mobile_de_scraper\\src\\scraper\\vendor_scraper.py", "source_location": "L274"}, {"caller_nid": "scraper_vendor_scraper_vendorscraper_extract_impressum", "callee": "search", "is_member_call": true, "source_file": "F:\\kod\\alphabots_rpa\\mobile_de_scraper\\src\\scraper\\vendor_scraper.py", "source_location": "L275"}, {"caller_nid": "scraper_vendor_scraper_vendorscraper_extract_impressum", "callee": "group", "is_member_call": true, "source_file": "F:\\kod\\alphabots_rpa\\mobile_de_scraper\\src\\scraper\\vendor_scraper.py", "source_location": "L277"}, {"caller_nid": "scraper_vendor_scraper_vendorscraper_extract_impressum", "callee": "debug", "is_member_call": true, "source_file": "F:\\kod\\alphabots_rpa\\mobile_de_scraper\\src\\scraper\\vendor_scraper.py", "source_location": "L280"}, {"caller_nid": "scraper_vendor_scraper_format_phone", "callee": "strip", "is_member_call": true, "source_file": "F:\\kod\\alphabots_rpa\\mobile_de_scraper\\src\\scraper\\vendor_scraper.py", "source_location": "L285"}, {"caller_nid": "scraper_vendor_scraper_format_phone", "callee": "sub", "is_member_call": true, "source_file": "F:\\kod\\alphabots_rpa\\mobile_de_scraper\\src\\scraper\\vendor_scraper.py", "source_location": "L287"}]}